eset/__init__.py
eset-0.0.2.dist-info/LICENSE
eset-0.0.2.dist-info/METADATA
eset-0.0.2.dist-info/WHEEL
eset-0.0.2.dist-info/top_level.txt
eset-0.0.2.dist-info/RECORD
